{
  "LEVEL_I": {
    "name": "Basic Level of Language Competence",
    "PRAGMATIC_COMPETENCE": {
      "name": "Pragmatic Competence - Functional Competence",
      "1_interact_socially_and_professionally": {
        "name": "Interact socially and professionally",
        "1.1": {
          "name": "Greet and introduce oneself or other people",
          "examples": [
            "Hello! My name is‚Ä¶ I am a friend of‚Ä¶",
            "Nice to meet you!",
            "This is my colleague."
          ],
          "vocabulary": [
            "Hello /h…ôňąl…ô ä/",
            "Hello (polite) /h…ôňąl…ô ä ňąp…íl.a…™t/",
            "Hello everyone /h…ôňąl…ô ä ňąev.ri.w Ćn/",
            "Goodbye /ňĆ…° ädňąba…™/",
            "See you tomorrow /siňź juňź t…ôňąm…ír.…ô ä/",
            "Introduce /ňĆ…™n.tr…ôňądjuňźs/",
            "Be called /biňź k…Ēňźld/",
            "Be /biňź/",
            "Surname /ňąs…úňź.ne…™m/",
            "Know, meet /n…ô ä miňźt/",
            "This (polite) /√į…™s p…ôňąla…™t/",
            "That (polite) /√į√¶t p…ôňąla…™t/",
            "Teacher /ňątiňź.t É…ôr/",
            "Classmate /ňąkl…Ďňźs.me…™t/",
            "Friend /frend/",
            "Mr. /ňąm…™s.t…ôr/",
            "Miss /m…™s/"
          ]
        },
        "1.2": {
          "name": "Make small talk",
          "examples": [
            "How have you been lately? Busy or not?",
            "The weather is nice today, but it might rain tomorrow.",
            "How was your weekend?",
            "Have you eaten?"
          ],
          "vocabulary": [
            "Today /t…ôňąde…™/",
            "Tomorrow /t…ôňąm…ír.…ô ä/",
            "Yesterday /ňąjes.t…ôr.de…™/",
            "Weather /ňąwe√į.…ôr/",
            "Good /…° äd/",
            "Not bad /n…ít b√¶d/",
            "Cold /k…ô äld/",
            "Hot /h…ít/",
            "Busy /ňąb…™z.i/",
            "Tired /ta…™…ôd/",
            "How? /ha ä/",
            "Recently /ňąriňź.s…ônt.li/",
            "Work /w…úňźk/",
            "Study /ňąst Ćd.i/",
            "Weekend /ňĆwiňźkňąend/",
            "Have a holiday /h√¶v …ô ňąh…íl.…ô.de…™/",
            "Where /we…ôr/",
            "Go /…°…ô ä/",
            "Come /k Ćm/",
            "Eat /iňźt/",
            "Drink /dr…™Ňčk/"
          ]
        },
        "1.3": {
          "name": "Extend, accept, or decline a simple invitation",
          "examples": [
            "How about having a meal together at noon?",
            "OK, where shall we go?",
            "Sorry, I have something to do at noon. Next time!"
          ],
          "vocabulary": [
            "Please /pliňźz/",
            "Invite /…™nňąva…™t/",
            "Come /k Ćm/",
            "Go /…°…ô ä/",
            "OK? /…ô äňąke…™/",
            "OK? /…ô äňąke…™/",
            "OK? /…ô äňąke…™/",
            "Sorry /ňąs…ír.i/",
            "Not OK /n…ít …ô äňąke…™/",
            "No problem /n…ô ä ňąpr…íb.l…ôm/",
            "OK! /…ô äňąke…™/",
            "Thank you /ňąőł√¶Ňčk juňź/",
            "Goodbye /ňĆ…° ädňąba…™/",
            "Tomorrow /t…ôňąm…ír.…ô ä/",
            "Evening /ňąiňźv.n…™Ňč/",
            "Together /t…ôňą…°e√į.…ôr/",
            "Eat meal /iňźt miňźl/",
            "Drink tea /dr…™Ňčk tiňź/",
            "Have free time /h√¶v friňź ta…™m/",
            "Time /ta…™m/"
          ]
        }
      },
      "2_exchange_information_describe_and_narrate": {
        "name": "Exchange information, describe, and narrate",
        "2.1": {
          "name": "Ask and give basic personal information",
          "examples": [
            "What is your surname? What is your name?",
            "I work at Tsinghua University. I am a postdoc.",
            "I don't have children yet."
          ],
          "vocabulary": [
            "Name /ne…™m/",
            "Be called /biňź k…Ēňźld/",
            "Surname /ňąs…úňź.ne…™m/",
            "This year /√į…™s j…™…ôr/",
            "How old (for children) /ha ä …ô äld f…Ēňź ňąt É…™l.dr…ôn/",
            "How old (general) /ha ä …ô äld ňąd íen.…ôr.…ôl/",
            "Where from /we…ôr fr…ím/",
            "Home /h…ô äm/",
            "Live /l…™v/",
            "Phone /f…ô än/",
            "Mobile phone /ňąm…ô ä.ba…™l f…ô än/",
            "Number /ňąn Ćm.b…ôr/",
            "Work /w…úňźk/",
            "Study /ňąst Ćd.i/",
            "Student /ňąstjuňź.d…ônt/",
            "Teacher /ňątiňź.t É…ôr/"
          ]
        },
        "2.2": {
          "name": "Ask and tell one's habits and hobbies",
          "examples": [
            "What are your hobbies?",
            "I like playing the piano, playing tennis and reading.",
            "On vacation he likes to travel abroad."
          ],
          "vocabulary": [
            "Like /la…™k/",
            "Love /l Ćv/",
            "Hobby /ňąh…íb.i/",
            "Often /ňą…íf.…ôn/",
            "Usually /ňąjuňź. íu.…ô.li/",
            "Weekend /ňĆwiňźkňąend/",
            "Sing /s…™Ňč/",
            "Play ball /ple…™ b…Ēňźl/",
            "Read books /riňźd b äks/",
            "Watch movies /w…ít É ňąmuňź.viz/",
            "Listen to music /ňąl…™s.…ôn tuňź ňąmjuňź.z…™k/",
            "Exercise /ňąek.s…ô.sa…™z/",
            "Go online /…°…ô ä ňą…ín.la…™n/",
            "Have fun /h√¶v f Ćn/",
            "What /w…ít/"
          ]
        },
        "2.3": {
          "name": "Ask and give information about routine activities",
          "examples": [
            "Which day of the week do you work from home?",
            "He goes to work at nine in the morning and gets off at five in the afternoon.",
            "Sometimes he eats at the restaurant downstairs, sometimes he goes out with colleagues."
          ],
          "vocabulary": [
            "Every day /ňąev.ri de…™/",
            "Morning /ňąm…Ēňź.n…™Ňč/",
            "Morning (late) /ňąm…Ēňź.n…™Ňč le…™t/",
            "Noon /nuňźn/",
            "Afternoon /ňĆ…Ďňźf.t…ôňąnuňźn/",
            "Evening /ňąiňźv.n…™Ňč/",
            "Get up /…°et  Ćp/",
            "Go to work /…°…ô ä tuňź w…úňźk/",
            "Go to class /…°…ô ä tuňź kl…Ďňźs/",
            "Finish class /ňąf…™n.…™ É kl…Ďňźs/",
            "Get off work /…°et …íf w…úňźk/",
            "Go home /…°…ô ä h…ô äm/",
            "Sleep /sliňźp/",
            "Eat /iňźt/",
            "Shower /ňą Éa ä.…ôr/",
            "Then /√įen/",
            "Then (immediate) /√įen …™ňąmiňź.di.…ôt/",
            "Then (later) /√įen ňąle…™.t…ôr/",
            "First /f…úňźst/",
            "Then (again) /√įen …ôňą…°en/"
          ]
        },
        "2.4": {
          "name": "Ask and give simple directions",
          "examples": [
            "Excuse me, where is the nearest cafe?",
            "The bank is not far from here. Go straight, turn left at the second intersection."
          ],
          "vocabulary": [
            "At, in /√¶t …™n/",
            "Where /we…ôr/",
            "How to go /ha ä tuňź …°…ô ä/",
            "Towards /t…ôňąw…Ēňźdz/",
            "Walk /w…Ēňźk/",
            "Left /left/",
            "Right /ra…™t/",
            "Front /fr Ćnt/",
            "Back /b√¶k/",
            "East /iňźst/",
            "South /sa äőł/",
            "West /west/",
            "North /n…Ēňźőł/",
            "Next to /nekst tuňź/",
            "Opposite /ňą…íp.…ô.z…™t/",
            "Intersection /ňĆ…™n.t…ôňąsek. É…ôn/",
            "Traffic light /ňątr√¶f.…™k la…™t/",
            "Ride /ra…™d/",
            "Vehicle /ňąviňź.…™.k…ôl/",
            "Road /r…ô äd/",
            "Stop /st…íp/",
            "Far /f…Ďňźr/",
            "Near /n…™…ôr/"
          ]
        },
        "2.5": {
          "name": "Make a simple plan",
          "examples": [
            "I want to go to the movies with a friend this weekend.",
            "Next month I will go to New York on a business trip.",
            "This summer I plan to travel to China with my family by plane. We want to go to Beijing first, then Shanghai."
          ],
          "vocabulary": [
            "Plan /pl√¶n/",
            "Think /őł…™Ňčk/",
            "Will /w…™l/",
            "Tomorrow /t…ôňąm…ír.…ô ä/",
            "Afternoon /ňĆ…Ďňźf.t…ôňąnuňźn/",
            "Weekend /ňĆwiňźkňąend/",
            "Together /t…ôňą…°e√į.…ôr/",
            "Go /…°…ô ä/",
            "Question particle /ňąkwes.t É…ôn ňąp…Ďňź.t…™.k…ôl/",
            "How about /ha ä …ôňąba ät/",
            "We /wiňź/",
            "First /f…úňźst/",
            "Then /√įen/",
            "Then (again) /√įen …ôňą…°en/",
            "Suggestion particle /s…ôňąd íes.t É…ôn ňąp…Ďňź.t…™.k…ôl/",
            "Good /…° äd/",
            "OK /…ô äňąke…™/"
          ]
        },
        "2.6": {
          "name": "Ask and give a simple description",
          "examples": [
            "What does he look like?",
            "My phone is black.",
            "This meeting room is not big, but many people come here for meetings."
          ],
          "vocabulary": [
            "How? /ha ä/",
            "What kind? /w…ít ka…™nd/",
            "Big /b…™…°/",
            "Small /sm…Ēňźl/",
            "Many /ňąmen.i/",
            "Few /fjuňź/",
            "Long /l…íŇč/",
            "Short / É…Ēňźt/",
            "Tall /t…Ēňźl/",
            "Short / É…Ēňźt/",
            "Fat /f√¶t/",
            "Thin /őł…™n/",
            "Color /ňąk Ćl.…ôr/",
            "Red /red/",
            "Yellow /ňąjel.…ô ä/",
            "Blue /bluňź/",
            "Green /…°riňźn/",
            "White /wa…™t/",
            "Black /bl√¶k/",
            "Beautiful /ňąbjuňź.t…™.f…ôl/",
            "Good-looking /ňĆ…° ädňąl äk.…™Ňč/",
            "New /njuňź/",
            "Old /…ô äld/",
            "Expensive /…™kňąspen.s…™v/",
            "Cheap /t Éiňźp/",
            "Hot /h…ít/",
            "Cold /k…ô äld/",
            "Delicious /d…™ňąl…™ É.…ôs/",
            "Good to drink /…° äd tuňź dr…™Ňčk/"
          ]
        },
        "2.7": {
          "name": "Give a simple narration of an experience",
          "examples": [
            "I have been to China, it was two years ago.",
            "Last week I went to Spain for a meeting."
          ],
          "vocabulary": [
            "Yesterday /ňąjes.t…ôr.de…™/",
            "Go /…°…ô ä/",
            "Particle (completed action) /ňąp…Ďňź.t…™.k…ôl/",
            "Particle (experience) /ňąp…Ďňź.t…™.k…ôl/",
            "First /f…úňźst/",
            "Then /√įen/",
            "Later /ňąle…™.t…ôr/",
            "Then (immediate) /√įen …™ňąmiňź.di.…ôt/",
            "Feel /fiňźl/",
            "Very /ňąver.i/",
            "Too /tuňź/",
            "Particle (exclamation) /ňąp…Ďňź.t…™.k…ôl/",
            "Really /ňąr…™…ô.li/",
            "Interesting /ňą…™n.tr…ô.st…™Ňč/",
            "Happy /ňąh√¶p.i/",
            "Tired /ta…™…ôd/"
          ]
        }
      },
      "3_express_feelings_attitudes_and_opinions": {
        "name": "Express feelings, attitudes, and opinions",
        "3.1": {
          "name": "Ask and express likes and dislikes",
          "examples": [
            "What do you like to eat?",
            "She really likes this new job.",
            "He doesn't really like living in this place because shopping and transportation are inconvenient."
          ],
          "vocabulary": [
            "Like /la…™k/",
            "Love /l Ćv/",
            "Dislike /d…™sňąla…™k/",
            "Most /m…ô äst/",
            "Especially /…™ňąspe É.…ôl.i/",
            "Very /ňąver.i/",
            "Very /ňąver.i/",
            "Still /st…™l/",
            "A little /…ô ňąl…™t.…ôl/",
            "What /w…ít/",
            "Question particle /ňąkwes.t É…ôn ňąp…Ďňź.t…™.k…ôl/"
          ]
        },
        "3.2": {
          "name": "Ask and respond to preferences",
          "examples": [
            "Compared to his previous life, he prefers his current life.",
            "These two computers are different.",
            "This room is brighter. Let's have our meeting here."
          ],
          "vocabulary": [
            "Like /la…™k/",
            "More /m…Ēňźr/",
            "Or /…Ēňźr/",
            "Compare /k…ômňąpe…ôr/",
            "Which /w…™t É/",
            "Which /w…™t É/",
            "Most /m…ô äst/",
            "Than /√į√¶n/",
            "And /√¶nd/",
            "Same /se…™m/",
            "Dislike /d…™sňąla…™k/"
          ]
        },
        "3.3": {
          "name": "Ask and express basic opinions",
          "examples": [
            "She is warm and very polite.",
            "I think this letter is too long, what do you think?",
            "For me, writing Chinese characters is the hardest."
          ],
          "vocabulary": [
            "Think /őł…™Ňčk/",
            "Consider /k…ônňąs…™d.…ôr/",
            "How? /ha ä/",
            "Good /…° äd/",
            "Correct /k…ôňąrekt/",
            "Incorrect /ňĆ…™n.k…ôňąrekt/",
            "Be /biňź/",
            "Not be /n…ít biňź/",
            "OK /…ô äňąke…™/",
            "Not OK /n…ít …ô äňąke…™/",
            "Should / É äd/",
            "Maybe /ňąme…™.bi/",
            "Really /ňąr…™…ô.li/",
            "Too /tuňź/",
            "Particle (exclamation) /ňąp…Ďňź.t…™.k…ôl/",
            "Question particle /ňąkwes.t É…ôn ňąp…Ďňź.t…™.k…ôl/",
            "Suggestion particle /s…ôňąd íes.t É…ôn ňąp…Ďňź.t…™.k…ôl/"
          ]
        }
      },
      "4_regulate_actions_with_others": {
        "name": "Regulate actions with others",
        "4.1": {
          "name": "Make and cancel a simple appointment or reservation",
          "examples": [
            "Shall we meet at ten on Wednesday morning?",
            "I no longer need that large meeting room."
          ],
          "vocabulary": [
            "Reserve /r…™ňąz…úňźv/",
            "Book /b äk/",
            "Seat /siňźt/",
            "Room /ruňźm/",
            "Time /ta…™m/",
            "What time /w…ít ta…™m/",
            "Tomorrow /t…ôňąm…ír.…ô ä/",
            "OK /…ô äňąke…™/",
            "Question particle /ňąkwes.t É…ôn ňąp…Ďňź.t…™.k…ôl/",
            "Sorry /ňąs…ír.i/",
            "Cancel /ňąk√¶n.s…ôl/",
            "Cannot /ňąk√¶n.…ít/",
            "Particle (change) /ňąp…Ďňź.t…™.k…ôl/",
            "Change /t Ée…™nd í/",
            "Suggestion particle /s…ôňąd íes.t É…ôn ňąp…Ďňź.t…™.k…ôl/"
          ]
        },
        "4.2": {
          "name": "Make and respond to a simple request",
          "examples": [
            "May I use this photocopier?",
            "Sure, go ahead.",
            "Ask Mr. Zhang about this question. Here is his phone number."
          ],
          "vocabulary": [
            "Please /pliňźz/",
            "Can /k√¶n/",
            "May /me…™/",
            "Help /help/",
            "A moment /…ô ňąm…ô ä.m…ônt/",
            "Question particle /ňąkwes.t É…ôn ňąp…Ďňź.t…™.k…ôl/",
            "OK /…ô äňąke…™/",
            "OK /…ô äňąke…™/",
            "No problem /n…ô ä ňąpr…íb.l…ôm/",
            "Sorry /ňąs…ír.i/",
            "Not OK /n…ít …ô äňąke…™/",
            "Now /na ä/",
            "Wait a moment /we…™t …ô ňąm…ô ä.m…ônt/",
            "Trouble /ňątr Ćb.…ôl/"
          ]
        },
        "4.3": {
          "name": "Make a simple order",
          "examples": [
            "I would like a cup of coffee.",
            "How much is this piece of clothing?",
            "It's too expensive, can you make it a little cheaper?"
          ],
          "vocabulary": [
            "Order /ňą…Ēňź.d…ôr/",
            "Want /w…ínt/",
            "This /√į…™s/",
            "That /√į√¶t/",
            "Come (order) /k Ćm/",
            "One portion /w Ćn ňąp…Ēňź. É…ôn/",
            "One bowl /w Ćn b…ô äl/",
            "One cup /w Ćn k Ćp/",
            "One (general) /w Ćn/",
            "Thank you /ňąőł√¶Ňčk juňź/",
            "Pay the bill /pe…™ √į…ô b…™l/",
            "How much /ha ä m Ćt É/"
          ]
        },
        "4.4": {
          "name": "Ask and give simple suggestions/advices",
          "examples": [
            "What do you think we should do?",
            "It's too late today. Come back tomorrow.",
            "The meeting is at nine tomorrow. You'd better come a little earlier."
          ],
          "vocabulary": [
            "Should / É äd/",
            "Can /k√¶n/",
            "Had better /h√¶d ňąbet.…ôr/",
            "Don't /d…ô änt/",
            "Do not /duňź n…ít/",
            "Try /tra…™/",
            "A moment /…ô ňąm…ô ä.m…ônt/",
            "Suggestion particle /s…ôňąd íes.t É…ôn ňąp…Ďňź.t…™.k…ôl/",
            "How about /ha ä …ôňąba ät/",
            "OK? /…ô äňąke…™/",
            "OK? /…ô äňąke…™/",
            "Think /őł…™Ňčk/",
            "Maybe /ňąme…™.bi/"
          ]
        }
      },
      "5_organize_the_speech": {
        "name": "Organize the speech",
        "5.1": {
          "name": "Use linkers to structure discourse and speech",
          "examples": [
            "Today let me first introduce two new colleagues, then discuss next month's work, and finally talk about the New Year's party.",
            "I really like living in this place. Why? First, there are shops and supermarkets nearby, so shopping is very convenient. Second, it's not far from my workplace, I can walk to work. Third, there is a park next to it, and I can go jogging there on weekends."
          ],
          "vocabulary": [
            "Then /√įen/",
            "Next /nekst/",
            "So /s…ô ä/",
            "But /b Ćt/",
            "But /b Ćt/",
            "Because /b…™ňąk…íz/",
            "Moreover /m…Ēňźňąr…ô ä.v…ôr/",
            "Although /…Ēňźlňą√į…ô ä/",
            "If /…™f/",
            "For example /f…Ēňźr …™…°ňąz…Ďňźm.p…ôl/",
            "For example /f…Ēňźr …™…°ňąz…Ďňźm.p…ôl/",
            "First /f…úňźst/",
            "Second /ňąsek.…ônd/",
            "Finally /ňąfa…™.n…ôl.i/",
            "First /f…úňźst/",
            "Then /√įen/",
            "That /√į√¶t/",
            "Also /ňą…Ēňźl.s…ô ä/",
            "Besides /b…™ňąsa…™dz/"
          ]
        }
      }
    },
    "LINGUISTIC_COMPETENCE_MORPHOLOGY_SYNTAX": {
      "name": "Linguistic Competence - Morphology and Syntax",
      "1": {
        "name": "Basic word order",
        "examples": [
          "My surname is Holden.",
          "He gets up at 7 every morning.",
          "Where do you work?",
          "Who are you calling?",
          "They are drinking tea in the office now.",
          "Do you go to work by bus?",
          "I go to the bookstore to buy two books.",
          "He uses a computer to type Chinese characters.",
          "I have dinner with a friend in the evening."
        ],
        "vocabulary": []
      },
      "2": {
        "name": "Word order ‚Äď topicalization",
        "examples": [
          "I have already read that document.",
          "What do you think about the thing I told you yesterday?"
        ],
        "vocabulary": []
      },
      "3": {
        "name": "Pronouns",
        "notes": "Personal: I, you, he, she, you (polite), you (plural), we, they, they (feminine), everyone, oneself; Demonstrative: this, that, other, every, each",
        "vocabulary": [
          "I /a…™/",
          "We /wiňź/",
          "You /juňź/",
          "You (plural) /juňź ňąpl ä…ô.r…ôl/",
          "He /hiňź/",
          "They /√įe…™/",
          "She / Éiňź/",
          "They (feminine) /√įe…™ ňąfem.…ô.n…™n/",
          "It /…™t/",
          "They /√įe…™/",
          "You (polite) /juňź p…ôňąla…™t/",
          "We (inclusive) /wiňź …™nňąkluňź.s…™v/",
          "We (inclusive) /wiňź …™nňąkluňź.s…™v/",
          "Oneself /w Ćnňąself/",
          "Others /ňą Ć√į.…ôz/",
          "Everyone /ňąev.ri.w Ćn/",
          "This /√į…™s/",
          "Here /h…™…ôr/",
          "Here /h…™…ôr/",
          "These /√įiňźz/",
          "That /√į√¶t/",
          "There /√įe…ôr/",
          "There /√įe…ôr/",
          "Those /√į…ô äz/",
          "Who /huňź/",
          "What /w…ít/",
          "Which /w…™t É/",
          "Where /we…ôr/",
          "Where /we…ôr/",
          "Which ones /w…™t É w Ćnz/",
          "How /ha ä/",
          "How? /ha ä/",
          "How /ha ä/"
        ]
      },
      "4": {
        "name": "Using śėĮ to identify a person or an object",
        "examples": [
          "He is my colleague.",
          "This is my phone."
        ],
        "vocabulary": []
      },
      "5": {
        "name": "Adverb",
        "notes": "all, also, still",
        "examples": [
          "We are all teachers.",
          "I also work here.",
          "These are the apples you wanted. Do you want to buy anything else?"
        ],
        "vocabulary": [
          "Not /n…ít/",
          "All /…Ēňźl/",
          "Very /ňąver.i/",
          "Extremely /…™kňąstriňźm.li/",
          "Too /tuňź/",
          "Most /m…ô äst/",
          "More /m…Ēňźr/",
          "Still /st…™l/",
          "Also /ňą…Ēňźl.s…ô ä/",
          "Again /…ôňą…°en/",
          "Then /√įen/",
          "Only then /ňą…ô än.li √įen/",
          "Again (future) /…ôňą…°en/",
          "First /f…úňźst/",
          "Just /d í Ćst/",
          "Just /d í Ćst/",
          "Already /…Ēňźlňąred.i/",
          "In progress /…™n ňąpr…ô ä.…°res/",
          "Exactly /…™…°ňąz√¶kt.li/",
          "Always /ňą…Ēňźl.we…™z/",
          "Suddenly /ňąs Ćd.…ôn.li/",
          "Suddenly /ňąs Ćd.…ôn.li/",
          "Immediately /…™ňąmiňź.di.…ôt.li/",
          "Immediately /…™ňąmiňź.di.…ôt.li/",
          "Hurry /ňąh Ćr.i/",
          "Hurry /ňąh Ćr.i/",
          "Each other /iňźt É ňą Ć√į.…ôr/",
          "Together /t…ôňą…°e√į.…ôr/",
          "Together /t…ôňą…°e√į.…ôr/",
          "Total /ňąt…ô ä.t…ôl/",
          "Completely /k…ômňąpliňźt.li/",
          "Especially /…™ňąspe É.…ôl.i/",
          "Very /ňąver.i/",
          "Very /ňąver.i/",
          "How /ha ä/",
          "Quite /kwa…™t/",
          "A bit /…ô b…™t/",
          "Almost /ňą…Ēňźl.m…ô äst/",
          "Probably /ňąpr…íb.…ô.bli/",
          "Approximately /…ôňąpr…ík.s…™.m…ôt.li/",
          "Actually /ňą√¶k.t Éu.…ô.li/",
          "Finally /ňąfa…™.n…ôl.i/"
        ]
      },
      "6": {
        "name": "Using śúČ to indicate possession",
        "examples": [
          "Do you have a computer?",
          "I have this book."
        ],
        "vocabulary": []
      },
      "7": {
        "name": "Yes-no question with Śźó",
        "examples": [
          "Is she your colleague?"
        ],
        "vocabulary": []
      },
      "8": {
        "name": "Negative sentences with šłć and ś≤°śúČ",
        "examples": [
          "I am not Teacher Zhang.",
          "I don't have a mobile phone."
        ],
        "vocabulary": [
          "Not /n…ít/",
          "Not /n…ít/",
          "Not have /n…ít h√¶v/",
          "Don't /d…ô änt/",
          "No need /n…ô ä niňźd/",
          "Don't /d…ô änt/"
        ]
      },
      "9": {
        "name": "Elliptical use of ŚĎĘ in a question",
        "examples": [
          "He is not a student, what about you?",
          "He has no siblings, what about you?"
        ],
        "vocabulary": []
      },
      "10": {
        "name": "Open-ended questions with interrogative pronouns",
        "notes": "who, what, which, where, how many, how much, when, how, how about, how",
        "vocabulary": [
          "Who /huňź/",
          "What /w…ít/",
          "Which /w…™t É/",
          "Where /we…ôr/",
          "Where /we…ôr/",
          "Which ones /w…™t É w Ćnz/",
          "How /ha ä/",
          "How? /ha ä/",
          "How /ha ä/",
          "How many /ha ä ňąmen.i/",
          "How much /ha ä m Ćt É/",
          "Why /wa…™/"
        ]
      },
      "11": {
        "name": "Common measure words",
        "notes": "general, volume, stick, strip, sheet, family, mouth, piece, handle, vehicle, unit, person, time, time, page, some",
        "vocabulary": [
          "General measure /ňąd íen.…ôr.…ôl ňąme í.…ôr/",
          "Polite measure /p…ôňąla…™t ňąme í.…ôr/",
          "Volume /ňąv…íl.juňźm/",
          "Cup /k Ćp/",
          "Sheet / Éiňźt/",
          "Piece /piňźs/",
          "Piece /piňźs/",
          "Strip /str…™p/",
          "Vehicle /ňąviňź.…™.k…ôl/",
          "Time /ta…™m/",
          "Moment /ňąm…ô ä.m…ônt/",
          "Point /p…Ē…™nt/",
          "A little /…ô ňąl…™t.…ôl/",
          "Some /s Ćm/",
          "Page /pe…™d í/",
          "Layer /ňąle…™.…ôr/",
          "Time (frequency) /ta…™m/",
          "Envelope /ňąen.v…ô.l…ô äp/",
          "Portion /ňąp…Ēňź. É…ôn/",
          "Kilometer /k…™ňąl…ím.…™.t…ôr/",
          "Kilogram /ňąk…™l.…ô.…°r√¶m/",
          "Jin (half kilogram) /d í…™n/",
          "Gram /…°r√¶m/",
          "Quarter (hour) /ňąkw…Ēňź.t…ôr/",
          "Mao (currency) /ma ä/",
          "Meter /ňąmiňź.t…ôr/",
          "Year (age) /j…™…ôr/",
          "Year /j…™…ôr/",
          "Month /m Ćnőł/",
          "Day /de…™/",
          "Date /de…™t/",
          "Minute /ňąm…™n.…™t/",
          "Segment /ňąse…°.m…ônt/",
          "Section /ňąsek. É…ôn/",
          "Mouth (measure) /ma äőł/",
          "Sentence /ňąsen.t…ôns/",
          "Chapter /ňąt É√¶p.t…ôr/",
          "Slice /sla…™s/",
          "Bottle /ňąb…ít.…ôl/",
          "Poem /ňąp…ô ä.…™m/",
          "Trip /tr…™p/",
          "Set /set/",
          "Kind /ka…™nd/",
          "Seat (large) /siňźt/"
        ]
      },
      "12": {
        "name": "Using particle ÁöĄ to indicate possession",
        "examples": [
          "This is my phone."
        ],
        "vocabulary": []
      },
      "13": {
        "name": "Affirmative-negative structure for yes-no questions",
        "examples": [
          "Does your office have a computer?",
          "Is he Mr. Zhang?",
          "Is this character correct?"
        ],
        "vocabulary": [
          "Is it? /…™z …™t/",
          "Is it good? /…™z …™t …° äd/",
          "Is it OK? /…™z …™t …ô äňąke…™/",
          "Is it possible? /…™z …™t ňąp…ís.…ô.b…ôl/"
        ]
      },
      "14": {
        "name": "Expressing date and time",
        "examples": [
          "Today is March 19, 2026.",
          "Tomorrow is Sunday.",
          "It's ten to nine now."
        ],
        "vocabulary": [
          "Year /j…™…ôr/",
          "Month /m Ćnőł/",
          "Day /de…™/",
          "Date /de…™t/",
          "Day /de…™/",
          "Week /wiňźk/",
          "Monday /ňąm Ćn.de…™/",
          "Tuesday /ňątjuňźz.de…™/",
          "Wednesday /ňąwenz.de…™/",
          "Thursday /ňąőł…úňźz.de…™/",
          "Friday /ňąfra…™.de…™/",
          "Saturday /ňąs√¶t.…ô.de…™/",
          "Sunday /ňąs Ćn.de…™/",
          "Sunday /ňąs Ćn.de…™/",
          "Hour /a ä…ôr/",
          "Minute /ňąm…™n.…™t/",
          "Quarter /ňąkw…Ēňź.t…ôr/",
          "Half /h…Ďňźf/",
          "Now /na ä/",
          "Today /t…ôňąde…™/",
          "Tomorrow /t…ôňąm…ír.…ô ä/",
          "Yesterday /ňąjes.t…ôr.de…™/",
          "Day before yesterday /de…™ b…™ňąf…Ēňźr ňąjes.t…ôr.de…™/",
          "Day after tomorrow /de…™ ňą…Ďňźf.t…ôr t…ôňąm…ír.…ô ä/",
          "Morning (late) /ňąm…Ēňź.n…™Ňč/",
          "Noon /nuňźn/",
          "Afternoon /ňĆ…Ďňźf.t…ôňąnuňźn/",
          "Morning /ňąm…Ēňź.n…™Ňč/",
          "Evening /ňąiňźv.n…™Ňč/",
          "Midnight /ňąm…™d.na…™t/",
          "Night /na…™t/",
          "Daytime /ňąde…™.ta…™m/",
          "Hour /a ä…ôr/",
          "Minute /ňąm…™n.…™t/",
          "Time /ta…™m/",
          "Time /ta…™m/",
          "Day /de…™/"
        ]
      },
      "15": {
        "name": "Indicating time sequence with šĽ•ŚČć, šĽ•Śźé",
        "examples": [
          "Before coming to work here, I worked at a company.",
          "After work, I go to school to pick up the child."
        ],
        "vocabulary": [
          "Before /b…™ňąf…Ēňźr/",
          "After /ňą…Ďňźf.t…ôr/"
        ]
      },
      "16": {
        "name": "Conjunction",
        "notes": "Addition: and, or, or; Contrast: but, but, but, although‚Ä¶ but‚Ä¶; Hypothesis: if‚Ä¶ then‚Ä¶; Cause and effect: because, so; Sequence: first‚Ä¶ then‚Ä¶ then‚Ä¶ finally‚Ä¶; Coordination: both‚Ä¶ and‚Ä¶, ‚Ä¶while‚Ä¶; Progression: not only‚Ä¶ but also‚Ä¶; Reference: for‚Ä¶; Illustration: for example, for instance",
        "vocabulary": [
          "And /√¶nd/",
          "With /w…™√į/",
          "And /√¶nd/",
          "Or /…Ēňźr/",
          "Or /…Ēňźr/",
          "Or /…Ēňźr/",
          "Because /b…™ňąk…íz/",
          "So /s…ô ä/",
          "But /b Ćt/",
          "But /b Ćt/",
          "But /b Ćt/",
          "But /b Ćt/",
          "However /ha äňąev.…ôr/",
          "If /…™f/",
          "If /…™f/",
          "Although /…Ēňźlňą√į…ô ä/",
          "Although /…Ēňźlňą√į…ô ä/",
          "Moreover /m…Ēňźňąr…ô ä.v…ôr/",
          "Furthermore /ňĆf…úňź.√į…ôňąm…Ēňźr/",
          "Not only /n…ít ňą…ô än.li/",
          "And /√¶nd/",
          "Then /√įen/",
          "Next /nekst/",
          "Thus /√į Ćs/",
          "Then /√įen/",
          "Because /b…™ňąk…íz/",
          "Therefore /ňą√įe…ô.f…Ēňźr/",
          "As long as /√¶z l…íŇč √¶z/",
          "Only if /ňą…ô än.li …™f/",
          "No matter /n…ô ä ňąm√¶t.…ôr/",
          "Regardless of /r…™ňą…°…Ďňźd.l…ôs …ív/",
          "Even if /ňąiňź.v…ôn …™f/",
          "Since /s…™ns/",
          "Besides /b…™ňąsa…™dz/",
          "For example /f…Ēňźr …™…°ňąz…Ďňźm.p…ôl/",
          "For example /f…Ēňźr …™…°ňąz…Ďňźm.p…ôl/"
        ]
      },
      "17": {
        "name": "Indicating age and price",
        "examples": [
          "My father is sixty years old.",
          "This book costs ten yuan."
        ],
        "vocabulary": [
          "Year (age) /j…™…ôr/",
          "Piece (money) /piňźs/",
          "Yuan /juňą…Ďňźn/",
          "Mao (currency) /ma ä/",
          "Jiao (currency) /d íja ä/",
          "Fen (currency) /fen/",
          "How much /ha ä m Ćt É/",
          "How many /ha ä ňąmen.i/"
        ]
      },
      "18": {
        "name": "Use of adjectives and degree adverbs",
        "examples": [
          "She is very beautiful.",
          "This book is very interesting."
        ],
        "vocabulary": [
          "Good /…° äd/",
          "Big /b…™…°/",
          "Small /sm…Ēňźl/",
          "Many /ňąmen.i/",
          "Few /fjuňź/",
          "Tall /t…Ēňźl/",
          "Low /l…ô ä/",
          "Long /l…íŇč/",
          "Short / É…Ēňźt/",
          "Far /f…Ďňźr/",
          "Near /n…™…ôr/",
          "Fast /f…Ďňźst/",
          "Slow /sl…ô ä/",
          "Early /ňą…úňź.li/",
          "Late /le…™t/",
          "Correct /k…ôňąrekt/",
          "Wrong /r…íŇč/",
          "True /truňź/",
          "False /f…íls/",
          "Expensive /…™kňąspen.s…™v/",
          "Cheap /t Éiňźp/",
          "Hot /h…ít/",
          "Cold /k…ô äld/",
          "Warm /w…Ēňźm/",
          "Cool /kuňźl/",
          "Comfortable /ňąk Ćm.f…ô.t…ô.b…ôl/",
          "Uncomfortable / Ćnňąk Ćm.f…ô.t…ô.b…ôl/",
          "Beautiful /ňąbjuňź.t…™.f…ôl/",
          "Ugly /ňą Ć…°.li/",
          "Delicious /d…™ňąl…™ É.…ôs/",
          "Nice to hear /na…™s tuňź h…™…ôr/",
          "Clean /kliňźn/",
          "Dirty /ňąd…úňź.ti/",
          "Busy /ňąb…™z.i/",
          "Tired /ta…™…ôd/",
          "Full /f äl/",
          "Hungry /ňąh ĆŇč.…°ri/",
          "Thirsty /ňąőł…úňź.sti/",
          "Happy /ňąh√¶p.i/",
          "Sad /s√¶d/",
          "Serious /ňąs…™…ô.ri.…ôs/",
          "Clear /kl…™…ôr/",
          "Safe /se…™f/",
          "Dangerous /ňąde…™n.d í…ôr.…ôs/",
          "Simple /ňąs…™m.p…ôl/",
          "Complex /ňąk…ím.pleks/",
          "Convenient /k…ônňąviňź.ni.…ônt/",
          "Lovely /ňąl Ćv.li/",
          "Scary /ňąske…ô.ri/",
          "Important /…™mňąp…Ēňź.t…ônt/",
          "Main /me…™n/",
          "Same /se…™m/",
          "All /…Ēňźl/",
          "All /…Ēňźl/",
          "Many /ňąmen.i/",
          "All /…Ēňźl/"
        ]
      },
      "19": {
        "name": "Exclamatory sentences",
        "examples": [
          "This book is really good!",
          "She is so beautiful!"
        ],
        "vocabulary": [
          "Ah /…Ďňź/",
          "Really /ňąr…™…ô.li/",
          "Too /tuňź/",
          "How /ha ä/",
          "Good /…° äd/",
          "So /s…ô ä/",
          "So /s…ô ä/"
        ]
      },
      "20": {
        "name": "Comparative structures",
        "examples": [
          "He is still the same as before.",
          "Chinese is different from English.",
          "I have studied Chinese longer than him, but my level is not as high as his.",
          "I like drinking coffee, but I like drinking tea even more.",
          "In our office, he works the longest."
        ],
        "vocabulary": [
          "Than /√į√¶n/",
          "Most /m…ô äst/",
          "More /m…Ēňźr/",
          "Same /se…™m/",
          "Not as good as /n…ít √¶z …° äd √¶z/",
          "Like /la…™k/"
        ]
      },
      "21": {
        "name": "Indicating quantitative and temporal limits with śúÄ",
        "examples": [
          "To do this job, it takes at least a week.",
          "Please let me know by next Monday at the latest."
        ],
        "vocabulary": [
          "Most /m…ô äst/",
          "Finally /ňąfa…™.n…ôl.i/",
          "Recently /ňąriňź.s…ônt.li/",
          "Best /best/"
        ]
      },
      "22": {
        "name": "Using ŚįĪ to identify a person or object",
        "examples": [
          "He is Professor Wang.",
          "That is my home."
        ],
        "vocabulary": []
      },
      "23": {
        "name": "Use ŚįĪ and śČć to indicate earliness and lateness",
        "examples": [
          "I arrived at the office at eight in the morning.",
          "I will call you as soon as I get to the office.",
          "She doesn't go to sleep until twelve at night."
        ],
        "vocabulary": [
          "Then (early) /√įen/",
          "Only then /ňą…ô än.li √įen/"
        ]
      },
      "24": {
        "name": "Using Śú® and location particles",
        "examples": [
          "Shanghai is in the south of China.",
          "The Red Cross is opposite the United Nations.",
          "His home is near the United Nations.",
          "The cafe is between the bookstore and the supermarket."
        ],
        "vocabulary": [
          "At /√¶t/",
          "On /…ín/",
          "Below /b…™ňąl…ô ä/",
          "Inside /ňĆ…™nňąsa…™d/",
          "Outside /ňĆa ätňąsa…™d/",
          "Front /fr Ćnt/",
          "Back /b√¶k/",
          "Left /left/",
          "Right /ra…™t/",
          "East /iňźst/",
          "South /sa äőł/",
          "West /west/",
          "North /n…Ēňźőł/",
          "Next to /nekst tuňź/",
          "Opposite /ňą…íp.…ô.z…™t/",
          "Middle /ňąm…™d.…ôl/",
          "Inside /ňĆ…™nňąsa…™d/",
          "Outside /ňĆa ätňąsa…™d/",
          "Above /…ôňąb Ćv/",
          "Below /b…™ňąl…ô ä/",
          "Front /fr Ćnt/",
          "Back /b√¶k/",
          "Left side /left sa…™d/",
          "Right side /ra…™t sa…™d/",
          "East side /iňźst sa…™d/",
          "South side /sa äőł sa…™d/",
          "West side /west sa…™d/",
          "North side /n…Ēňźőł sa…™d/"
        ]
      },
      "25": {
        "name": "Using particle ÁöĄ to indicate attributives",
        "examples": [
          "He gave me a beautiful coat.",
          "This is the tea I bought for you.",
          "The person in front is my sister."
        ],
        "vocabulary": []
      },
      "26": {
        "name": "Using śėĮ or śúČ to indicate the presence/existence",
        "examples": [
          "Opposite the bank is a supermarket.",
          "There are many people there.",
          "There are two restaurants on that street."
        ],
        "vocabulary": [
          "Is /…™z/",
          "There is /√įe…ôr …™z/",
          "At /√¶t/"
        ]
      },
      "27": {
        "name": "Preposition",
        "notes": "to, for, to, with, from‚Ä¶ to‚Ä¶, towards, toward",
        "vocabulary": [
          "At /√¶t/",
          "From /fr…ím/",
          "To /tuňź/",
          "For /f…Ēňźr/",
          "About /…ôňąba ät/",
          "With /w…™√į/",
          "And /√¶nd/",
          "With /w…™√į/",
          "For /f…Ēňźr/",
          "In order to /…™n ňą…Ēňź.d…ôr tuňź/",
          "Because /b…™ňąk…íz/",
          "Due to /djuňź tuňź/",
          "By /ba…™/",
          "By (passive) /ba…™/",
          "Called /k…Ēňźld/",
          "Let /let/",
          "To /tuňź/",
          "Towards /t…ôňąw…Ēňźdz/",
          "Towards /t…ôňąw…Ēňźdz/",
          "Towards /t…ôňąw…Ēňźdz/",
          "To /tuňź/",
          "At /√¶t/",
          "Since /s…™ns/",
          "According to /…ôňąk…Ēňź.d…™Ňč tuňź/",
          "Based on /be…™st …ín/",
          "Through /őłruňź/",
          "Via /ňąva…™.…ô/",
          "Except /…™kňąsept/",
          "As /√¶z/",
          "With /w…™√į/",
          "Take /te…™k/",
          "By /ba…™/"
        ]
      },
      "28": {
        "name": "Make a suggestion with particle Śźß",
        "examples": [
          "Let's go watch a movie!"
        ],
        "vocabulary": []
      },
      "29": {
        "name": "Make a speculation/assumption with the particle Śźß",
        "examples": [
          "You are Mr. Wang, aren't you?",
          "This piece of clothing is yours, isn't it?"
        ],
        "vocabulary": []
      },
      "30": {
        "name": "Tag questions with śÄéšĻąś†∑, Ś•ĹŚźó, ŚŹĮšĽ•Śźó, Ť°ĆŚźó, śėĮŚźó/śėĮšłćśėĮ",
        "examples": [
          "How about going for coffee after work?",
          "I'll call you at three, OK?",
          "You like to wear white clothes, don't you?"
        ],
        "vocabulary": [
          "How about /ha ä …ôňąba ät/",
          "OK? /…ô äňąke…™/",
          "OK? /…ô äňąke…™/",
          "OK? /…ô äňąke…™/",
          "Right? /ra…™t/",
          "Is it? /…™z …™t/"
        ]
      },
      "31": {
        "name": "Verb reduplication and verb with šłÄšłč(ŚĄŅ)",
        "examples": [
          "Let me think.",
          "Let me introduce you."
        ],
        "vocabulary": [
          "A moment /…ô ňąm…ô ä.m…ônt/",
          "A moment /…ô ňąm…ô ä.m…ônt/"
        ]
      },
      "32": {
        "name": "Imperative sentences",
        "examples": [
          "Please come in! Please sit!",
          "Don't sit there! Don't speak!"
        ],
        "vocabulary": [
          "Please /pliňźz/",
          "Don't /d…ô änt/",
          "Don't /d…ô änt/"
        ]
      },
      "33": {
        "name": "Modal verbs",
        "examples": [
          "I want to buy a cup of coffee.",
          "I have a meeting this afternoon.",
          "I plan to travel to China this summer.",
          "Can you call me now?",
          "You are not allowed to eat here.",
          "He can't speak Chinese.",
          "You should ask Xiao Wang about this.",
          "I asked him to come, but he doesn't want to.",
          "Do you need my help? No, thanks!"
        ],
        "vocabulary": [
          "Can /k√¶n/",
          "Be able to /bi ňąe…™.b…ôl tuňź/",
          "Can /k√¶n/",
          "May /me…™/",
          "Maybe /ňąme…™.bi/",
          "Should / É äd/",
          "Should / É äd/",
          "Should / É äd/",
          "Must /m Ćst/",
          "Will /w…™l/",
          "Want /w…ínt/",
          "Be willing /bi ňąw…™l.…™Ňč/",
          "Be willing /bi ňąw…™l.…™Ňč/",
          "Dare /de…ôr/"
        ]
      },
      "34": {
        "name": "Pivotal sentences",
        "notes": "ask/let/want + Verb Phrase",
        "examples": [
          "I asked him to help me.",
          "I asked her to call me.",
          "My wife wants me to get off work at four today."
        ],
        "vocabulary": []
      },
      "35": {
        "name": "Indirect speech",
        "examples": [
          "He said he also works at Tsinghua University.",
          "I asked him where he works.",
          "He asked me if I had a pen."
        ],
        "vocabulary": [
          "Say /se…™/",
          "Ask /…Ďňźsk/",
          "Tell /tel/",
          "Answer /ňą…Ďňźn.s…ôr/"
        ]
      },
      "36": {
        "name": "Using śėĮ‚Ä¶‚Ä¶ÁöĄ to specify a feature or to emphasize details",
        "examples": [
          "My car is black.",
          "That table is round.",
          "We met in Beijing last year.",
          "Which year did you come to work at Tsinghua University?"
        ],
        "vocabulary": []
      },
      "37": {
        "name": "Durative/Progressive aspect",
        "examples": [
          "The children are sleeping.",
          "Mr. Wang is in a meeting, please wait a moment."
        ],
        "vocabulary": [
          "In progress /…™n ňąpr…ô ä.…°res/",
          "In progress /…™n ňąpr…ô ä.…°res/",
          "Particle (durative) /ňąp…Ďňź.t…™.k…ôl/"
        ]
      },
      "38": {
        "name": "Using sentence-final particle šļÜ to inform a new situation or change",
        "examples": [
          "It's getting dark.",
          "He is sick.",
          "He no longer works here.",
          "It's seven o'clock, time to go home.",
          "Look, it's going to rain.",
          "You may leave now."
        ],
        "vocabulary": []
      },
      "39": {
        "name": "Using šļÜ to quantify an action or event in the past",
        "examples": [
          "I watched a movie on the weekend.",
          "He rested for two hours.",
          "I went to see him three times."
        ],
        "vocabulary": []
      },
      "40": {
        "name": "Using ŤŅá to indicate an experience",
        "examples": [
          "I have been to China."
        ],
        "vocabulary": []
      },
      "41": {
        "name": "Using šľö to indicate possibility or likelihood",
        "examples": [
          "Do you think the boss will agree?",
          "He should come today."
        ],
        "vocabulary": []
      },
      "42": {
        "name": "Using ÁĚÄ to describe a place or someone's clothing",
        "examples": [
          "There is a person standing outside the door.",
          "A painting is hanging on the wall.",
          "He is wearing a black coat."
        ],
        "vocabulary": []
      },
      "43": {
        "name": "Using Śĺó to describe/evaluate an action",
        "examples": [
          "He speaks Chinese very quickly.",
          "Your Chinese characters are written very beautifully."
        ],
        "vocabulary": []
      },
      "44": {
        "name": "Simple directional verb complement",
        "examples": [
          "When will he come back?",
          "He went out to buy something."
        ],
        "vocabulary": [
          "Come /k Ćm/",
          "Go /…°…ô ä/",
          "Up / Ćp/",
          "Down /da än/",
          "In /…™n/",
          "Out /a ät/",
          "Back /b√¶k/",
          "Over /ňą…ô ä.v…ôr/",
          "Up / Ćp/",
          "Open /ňą…ô ä.p…ôn/",
          "Come up /k Ćm  Ćp/",
          "Go up /…°…ô ä  Ćp/",
          "Come down /k Ćm da än/",
          "Go down /…°…ô ä da än/",
          "Come in /k Ćm …™n/",
          "Go in /…°…ô ä …™n/",
          "Come out /k Ćm a ät/",
          "Go out /…°…ô ä a ät/",
          "Come back /k Ćm b√¶k/",
          "Go back /…°…ô ä b√¶k/",
          "Come over /k Ćm ňą…ô ä.v…ôr/",
          "Go over /…°…ô ä ňą…ô ä.v…ôr/",
          "Get up /…°et  Ćp/"
        ]
      },
      "45": {
        "name": "Using the adverb ŚÜć to express the duplication of an action in the future",
        "examples": [
          "If he comes to see me again, tell him I went out for lunch."
        ],
        "vocabulary": []
      },
      "46": {
        "name": "Using the adverb šłÄÁõī to express continuity or indicate straight direction",
        "examples": [
          "He has been in meetings from morning until now.",
          "Go straight for five minutes and you'll arrive."
        ],
        "vocabulary": []
      }
    },
    "LINGUISTIC_COMPETENCE_LEXIS": {
      "name": "Linguistic Competence - Lexis",
      "1": {
        "name": "Relationship",
        "notes": "Family: dad, mom, older brother, older sister, younger brother, younger sister, siblings, husband/wife, family; Colleagues and friends: classmate, colleague, friend, boyfriend, girlfriend",
        "vocabulary": [
          "Dad /d√¶d/",
          "Mom /m…ím/",
          "Older brother /ňą…ô äl.d…ôr ňąbr Ć√į.…ôr/",
          "Older sister /ňą…ô äl.d…ôr ňąs…™s.t…ôr/",
          "Younger brother /ňąj ĆŇč.…°…ôr ňąbr Ć√į.…ôr/",
          "Younger sister /ňąj ĆŇč.…°…ôr ňąs…™s.t…ôr/",
          "Grandpa /ňą…°r√¶n.p…Ďňź/",
          "Grandma /ňą…°r√¶n.m…Ďňź/",
          "Son /s Ćn/",
          "Daughter /ňąd…Ēňź.t…ôr/",
          "Child /t Éa…™ld/",
          "Friend /frend/",
          "Boyfriend /ňąb…Ē…™.frend/",
          "Girlfriend /ňą…°…úňźl.frend/",
          "Classmate /ňąkl…Ďňźs.me…™t/",
          "Colleague /ňąk…íl.iňź…°/",
          "Teacher /ňątiňź.t É…ôr/",
          "Student /ňąstjuňź.d…ônt/",
          "Mr. /ňąm…™s.t…ôr/",
          "Miss /m…™s/",
          "Family /ňąf√¶m.…ôl.i/",
          "Spouse /spa äs/",
          "Relative /ňąrel.…ô.t…™v/",
          "Neighbor /ňąne…™.b…ôr/"
        ]
      },
      "2": {
        "name": "Professions and workplace",
        "notes": "Profession: teacher, student, staff, doctor, secretary; Workplace: United Nations, department, office, computer, print, copy, introduce, self-introduction, paper, meeting, business trip, prepare, work overtime, ask for leave",
        "vocabulary": [
          "Work /w…úňźk/",
          "Teacher /ňątiňź.t É…ôr/",
          "Student /ňąstjuňź.d…ônt/",
          "Doctor /ňąd…ík.t…ôr/",
          "Nurse /n…úňźs/",
          "Worker /ňąw…úňź.k…ôr/",
          "Driver /ňądra…™.v…ôr/",
          "Businessperson /ňąb…™z.n…™s.p…úňź.s…ôn/",
          "Manager /ňąm√¶n.…™.d í…ôr/",
          "Writer /ňąra…™.t…ôr/",
          "Painter /ňąpe…™n.t…ôr/",
          "Actor /ňą√¶k.t…ôr/",
          "Chef / Éef/",
          "Waiter /ňąwe…™.t…ôr/",
          "Police officer /p…ôňąliňźs ňą…íf.…™.s…ôr/",
          "Lawyer /ňąl…Ēňź.j…ôr/",
          "Office /ňą…íf.…™s/",
          "Company /ňąk Ćm.p…ô.ni/",
          "Hospital /ňąh…ís.p…™.t…ôl/",
          "School /skuňźl/",
          "Factory /ňąf√¶k.t…ôr.i/",
          "Restaurant /ňąres.t…ôr.…ínt/",
          "Bank /b√¶Ňčk/"
        ]
      },
      "3": {
        "name": "Cardinal number 0 to 100 and ordinal numeral",
        "notes": "zero, one, ten, twenty-five, forty, eighty-six, one hundred; first, second, third‚Ä¶",
        "vocabulary": [
          "Zero /ňąz…™…ô.r…ô ä/",
          "One /w Ćn/",
          "Two /tuňź/",
          "Three /őłriňź/",
          "Four /f…Ēňźr/",
          "Five /fa…™v/",
          "Six /s…™ks/",
          "Seven /ňąsev.…ôn/",
          "Eight /e…™t/",
          "Nine /na…™n/",
          "Ten /ten/",
          "Eleven /…™ňąlev.…ôn/",
          "Twelve /twelv/",
          "Twenty /ňątwen.ti/",
          "Twenty-one /ňątwen.ti w Ćn/",
          "Thirty /ňąőł…úňź.ti/",
          "Forty /ňąf…Ēňź.ti/",
          "Fifty /ňąf…™f.ti/",
          "Sixty /ňąs…™k.sti/",
          "Seventy /ňąsev.…ôn.ti/",
          "Eighty /ňąe…™.ti/",
          "Ninety /ňąna…™n.ti/",
          "One hundred /w Ćn ňąh Ćn.dr…ôd/",
          "First /f…úňźst/",
          "Second /ňąsek.…ônd/",
          "Third /őł…úňźd/"
        ]
      },
      "4": {
        "name": "Countries, cities, and nationalities",
        "notes": "e.g. China, Beijing, Shanghai, Chinese",
        "vocabulary": [
          "China /ňąt Éa…™.n…ô/",
          "Beijing /be…™ňąd í…™Ňč/",
          "Shanghai / É√¶Ňčňąha…™/",
          "United States /juňąna…™.t…™d ste…™ts/",
          "United Kingdom /juňąna…™.t…™d ňąk…™Ňč.d…ôm/",
          "France /fr…Ďňźns/",
          "Germany /ňąd í…úňź.m…ô.ni/",
          "Japan /d í…ôňąp√¶n/",
          "South Korea /sa äőł k…ôňąriňź.…ô/",
          "Chinese /t Éa…™ňąniňźz/",
          "American /…ôňąmer.…™.k…ôn/",
          "Foreigner /ňąf…ír.…ô.n…ôr/"
        ]
      },
      "5": {
        "name": "Languages",
        "notes": "Chinese, English, French, Spanish, Russian, Arabic",
        "vocabulary": [
          "Chinese /t Éa…™ňąniňźz/",
          "Chinese /t Éa…™ňąniňźz/",
          "English /ňą…™Ňč.…°l…™ É/",
          "English /ňą…™Ňč.…°l…™ É/",
          "Foreign language /ňąf…ír.…™n ňąl√¶Ňč.…°w…™d í/",
          "Language /ňąl√¶Ňč.…°w…™d í/"
        ]
      },
      "6": {
        "name": "Learning",
        "notes": "study, class, class, grammar, spoken language, Chinese character, new word, review, difficult, easy, homework, exam, practice, example",
        "vocabulary": [
          "Study /ňąst Ćd.i/",
          "Learn /l…úňźn/",
          "Read /riňźd/",
          "Write /ra…™t/",
          "Listen /ňąl…™s.…ôn/",
          "Speak /spiňźk/",
          "Read books /riňźd b äks/",
          "Read books /riňźd b äks/",
          "Go to class /…°…ô ä tuňź kl…Ďňźs/",
          "Finish class /ňąf…™n.…™ É kl…Ďňźs/",
          "Exam /…™…°ňąz√¶m/",
          "Review /r…™ňąvjuňź/",
          "Practice /ňąpr√¶k.t…™s/",
          "Homework /ňąh…ô äm.w…úňźk/",
          "Word /w…úňźd/",
          "Sentence /ňąsen.t…ôns/",
          "Text /tekst/",
          "Teacher /ňątiňź.t É…ôr/",
          "Student /ňąstjuňź.d…ônt/",
          "School /skuňźl/",
          "Classroom /ňąkl…Ďňźs.ruňźm/",
          "Library /ňąla…™.br…ôr.i/",
          "Chinese /t Éa…™ňąniňźz/",
          "Chinese /t Éa…™ňąniňźz/"
        ]
      },
      "7": {
        "name": "Expression of time",
        "notes": "year, month, day, day, week, now, hour, minute, half, quarter, to, morning, morning, noon, afternoon, evening, yesterday, today, tomorrow, time, hour, minute",
        "vocabulary": [
          "Year /j…™…ôr/",
          "Month /m Ćnőł/",
          "Day /de…™/",
          "Date /de…™t/",
          "Day /de…™/",
          "Week /wiňźk/",
          "Monday /ňąm Ćn.de…™/",
          "Tuesday /ňątjuňźz.de…™/",
          "Wednesday /ňąwenz.de…™/",
          "Thursday /ňąőł…úňźz.de…™/",
          "Friday /ňąfra…™.de…™/",
          "Saturday /ňąs√¶t.…ô.de…™/",
          "Sunday /ňąs Ćn.de…™/",
          "Sunday /ňąs Ćn.de…™/",
          "Hour /a ä…ôr/",
          "Minute /ňąm…™n.…™t/",
          "Quarter /ňąkw…Ēňź.t…ôr/",
          "Half /h…Ďňźf/",
          "Now /na ä/",
          "Today /t…ôňąde…™/",
          "Tomorrow /t…ôňąm…ír.…ô ä/",
          "Yesterday /ňąjes.t…ôr.de…™/",
          "Day before yesterday /de…™ b…™ňąf…Ēňźr ňąjes.t…ôr.de…™/",
          "Day after tomorrow /de…™ ňą…Ďňźf.t…ôr t…ôňąm…ír.…ô ä/",
          "Morning /ňąm…Ēňź.n…™Ňč/",
          "Morning (late) /ňąm…Ēňź.n…™Ňč/",
          "Noon /nuňźn/",
          "Afternoon /ňĆ…Ďňźf.t…ôňąnuňźn/",
          "Evening /ňąiňźv.n…™Ňč/",
          "Midnight /ňąm…™d.na…™t/",
          "Night /na…™t/",
          "Daytime /ňąde…™.ta…™m/",
          "Hour /a ä…ôr/",
          "Minute /ňąm…™n.…™t/",
          "Time /ta…™m/",
          "Time /ta…™m/"
        ]
      },
      "8": {
        "name": "Food and drink",
        "notes": "eat, drink, water, tea, coffee, milk, alcohol, Chinese food, dish, rice, noodles, delicious, tasty, fragrant, hungry, thirsty, fruit, apple, banana, orange",
        "vocabulary": [
          "Eat /iňźt/",
          "Drink /dr…™Ňčk/",
          "Meal /miňźl/",
          "Dish /d…™ É/",
          "Breakfast /ňąbrek.f…ôst/",
          "Lunch /l Ćnt É/",
          "Dinner /ňąd…™n.…ôr/",
          "Rice /ra…™s/",
          "Noodles /ňąnuňź.d…ôlz/",
          "Bread /bred/",
          "Baozi (stuffed bun) /ňąba ä.z…™/",
          "Dumpling /ňąd Ćm.pl…™Ňč/",
          "Egg /e…°/",
          "Meat /miňźt/",
          "Fish /f…™ É/",
          "Milk /m…™lk/",
          "Water /ňąw…Ēňź.t…ôr/",
          "Tea /tiňź/",
          "Coffee /ňąk…íf.i/",
          "Fruit /fruňźt/",
          "Apple /ňą√¶p.…ôl/",
          "Delicious /d…™ňąl…™ É.…ôs/",
          "Good to drink /…° äd tuňź dr…™Ňčk/",
          "Hungry /ňąh ĆŇč.…°ri/",
          "Thirsty /ňąőł…úňź.sti/",
          "Full /f äl/"
        ]
      },
      "9": {
        "name": "Purchasing and money",
        "notes": "buy, thing, money, piece, yuan, change, change, expensive, cheap",
        "vocabulary": [
          "Buy /ba…™/",
          "Sell /sel/",
          "Money /ňąm Ćn.i/",
          "How much /ha ä m Ćt É/",
          "Piece (money) /piňźs/",
          "Yuan /juňą…Ďňźn/",
          "Mao (currency) /ma ä/",
          "Jiao (currency) /d íja ä/",
          "Fen (currency) /fen/",
          "Expensive /…™kňąspen.s…™v/",
          "Cheap /t Éiňźp/",
          "Ticket /ňąt…™k.…™t/",
          "Bus ticket /b Ćs ňąt…™k.…™t/",
          "Plane ticket /ple…™n ňąt…™k.…™t/",
          "Admission ticket /…ôdňąm…™ É.…ôn ňąt…™k.…™t/",
          "Card /k…Ďňźd/",
          "Credit card /ňąkred.…™t k…Ďňźd/",
          "Backpack /ňąb√¶k.p√¶k/",
          "Clothes /kl…ô ä√įz/",
          "Shop / É…íp/",
          "Supermarket /ňąsuňź.p…ô.m…Ďňź.k…™t/",
          "Market /ňąm…Ďňź.k…™t/"
        ]
      },
      "10": {
        "name": "Public places and buildings",
        "notes": "restaurant, classroom, cafeteria, bookstore, library, school, elementary school, middle school, university, park, supermarket, bank, hospital, station, train station, airport, company, shop, bar, subway station, dining hall",
        "vocabulary": [
          "School /skuňźl/",
          "Library /ňąla…™.br…ôr.i/",
          "Classroom /ňąkl…Ďňźs.ruňźm/",
          "Office /ňą…íf.…™s/",
          "Hospital /ňąh…ís.p…™.t…ôl/",
          "Shop / É…íp/",
          "Supermarket /ňąsuňź.p…ô.m…Ďňź.k…™t/",
          "Market /ňąm…Ďňź.k…™t/",
          "Restaurant /ňąres.t…ôr.…ínt/",
          "Restaurant /ňąres.t…ôr.…ínt/",
          "Hotel /h…ô äňątel/",
          "Hotel /h…ô äňątel/",
          "Park /p…Ďňźk/",
          "Zoo /zuňź/",
          "Cinema /ňąs…™n.…ô.m…ô/",
          "Gymnasium /d í…™mňąne…™.zi.…ôm/",
          "Bank /b√¶Ňčk/",
          "Airport /ňąe…ô.p…Ēňźt/",
          "Station /ňąste…™. É…ôn/",
          "Train station /tre…™n ňąste…™. É…ôn/",
          "Subway station /ňąs Ćb.we…™ ňąste…™. É…ôn/",
          "Square /skwe…ôr/"
        ]
      },
      "11": {
        "name": "Home / House",
        "notes": "place, home, house, building, room, bathroom, door, window, wall, cabinet, bed, table, chair, lamp, TV, telephone, mobile phone, garden",
        "vocabulary": [
          "Home /h…ô äm/",
          "House /ha äs/",
          "Room /ruňźm/",
          "Room /ruňźm/",
          "Door /d…Ēňźr/",
          "Window /ňąw…™n.d…ô ä/",
          "Bed /bed/",
          "Table /ňąte…™.b…ôl/",
          "Chair /t Ée…ôr/",
          "Sofa /ňąs…ô ä.f…ô/",
          "Cabinet /ňąk√¶b.…™.n…ôt/",
          "Lamp /l√¶mp/",
          "Phone /f…ô än/",
          "TV /ňĆtiňźňąviňź/",
          "Computer /k…ômňąpjuňź.t…ôr/",
          "Kitchen /ňąk…™t É.…™n/",
          "Toilet /ňąt…Ē…™.l…ôt/",
          "Bathroom /ňąb…Ďňźőł.ruňźm/",
          "Shower /ňą Éa ä.…ôr/",
          "Sleep /sliňźp/"
        ]
      },
      "12": {
        "name": "Common adjective to describe a person or an object",
        "vocabulary": [
          "Good /…° äd/",
          "Big /b…™…°/",
          "Small /sm…Ēňźl/",
          "Many /ňąmen.i/",
          "Few /fjuňź/",
          "Tall /t…Ēňźl/",
          "Low /l…ô ä/",
          "Long /l…íŇč/",
          "Short / É…Ēňźt/",
          "Far /f…Ďňźr/",
          "Near /n…™…ôr/",
          "Fast /f…Ďňźst/",
          "Slow /sl…ô ä/",
          "Early /ňą…úňź.li/",
          "Late /le…™t/",
          "Correct /k…ôňąrekt/",
          "Wrong /r…íŇč/",
          "True /truňź/",
          "False /f…íls/",
          "Expensive /…™kňąspen.s…™v/",
          "Cheap /t Éiňźp/",
          "Hot /h…ít/",
          "Cold /k…ô äld/",
          "Warm /w…Ēňźm/",
          "Cool /kuňźl/",
          "Comfortable /ňąk Ćm.f…ô.t…ô.b…ôl/",
          "Uncomfortable / Ćnňąk Ćm.f…ô.t…ô.b…ôl/",
          "Beautiful /ňąbjuňź.t…™.f…ôl/",
          "Good-looking /ňĆ…° ädňąl äk.…™Ňč/",
          "Ugly /ňą Ć…°.li/",
          "Delicious /d…™ňąl…™ É.…ôs/",
          "Nice to hear /na…™s tuňź h…™…ôr/",
          "Clean /kliňźn/",
          "Dirty /ňąd…úňź.ti/",
          "Busy /ňąb…™z.i/",
          "Tired /ta…™…ôd/",
          "Happy /ňąh√¶p.i/",
          "Serious /ňąs…™…ô.ri.…ôs/",
          "Clear /kl…™…ôr/",
          "Safe /se…™f/",
          "Dangerous /ňąde…™n.d í…ôr.…ôs/",
          "Simple /ňąs…™m.p…ôl/",
          "Complex /ňąk…ím.pleks/",
          "Convenient /k…ônňąviňź.ni.…ônt/",
          "Important /…™mňąp…Ēňź.t…ônt/",
          "Same /se…™m/",
          "New /njuňź/",
          "Old /…ô äld/"
        ]
      },
      "13": {
        "name": "Common adverbs of degree",
        "notes": "very, extremely, extremely, not very, too, really, a little, relatively",
        "vocabulary": [
          "Very /ňąver.i/",
          "Extremely /…™kňąstriňźm.li/",
          "Too /tuňź/",
          "Most /m…ô äst/",
          "More /m…Ēňźr/",
          "Especially /…™ňąspe É.…ôl.i/",
          "Very /ňąver.i/",
          "How /ha ä/",
          "Quite /kwa…™t/",
          "A bit /…ô b…™t/",
          "Almost /ňą…Ēňźl.m…ô äst/"
        ]
      },
      "14": {
        "name": "Hobbies",
        "vocabulary": [
          "Like /la…™k/",
          "Hobby /ňąh…íb.i/",
          "Sing /s…™Ňč/",
          "Play ball /ple…™ b…Ēňźl/",
          "Read books /riňźd b äks/",
          "Watch movies /w…ít É ňąmuňź.viz/",
          "Listen to music /ňąl…™s.…ôn tuňź ňąmjuňź.z…™k/",
          "Exercise /ňąek.s…ô.sa…™z/",
          "Go online /…°…ô ä ňą…ín.la…™n/",
          "Have fun /h√¶v f Ćn/",
          "Travel /ňątr√¶v.…ôl/",
          "Photo /ňąf…ô ä.t…ô ä/",
          "Take photos /te…™k ňąf…ô ä.t…ô äz/"
        ]
      },
      "15": {
        "name": "Daily routine",
        "vocabulary": [
          "Get up /…°et  Ćp/",
          "Go to work /…°…ô ä tuňź w…úňźk/",
          "Go to class /…°…ô ä tuňź kl…Ďňźs/",
          "Finish class /ňąf…™n.…™ É kl…Ďňźs/",
          "Get off work /…°et …íf w…úňźk/",
          "Go home /…°…ô ä h…ô äm/",
          "Sleep /sliňźp/",
          "Eat /iňźt/",
          "Shower /ňą Éa ä.…ôr/",
          "Every day /ňąev.ri de…™/",
          "Morning /ňąm…Ēňź.n…™Ňč/",
          "Morning (late) /ňąm…Ēňź.n…™Ňč/",
          "Noon /nuňźn/",
          "Afternoon /ňĆ…Ďňźf.t…ôňąnuňźn/",
          "Evening /ňąiňźv.n…™Ňč/",
          "Then /√įen/",
          "First /f…úňźst/",
          "Then (again) /√įen …ôňą…°en/",
          "Then (immediate) /√įen …™ňąmiňź.di.…ôt/",
          "Only then /ňą…ô än.li √įen/"
        ]
      },
      "16": {
        "name": "Clothes",
        "notes": "clothes, coat, overcoat, shirt, pants, skirt, shoes",
        "vocabulary": [
          "Clothes /kl…ô ä√įz/",
          "Wear /we…ôr/",
          "Pants /p√¶nts/",
          "Skirt /sk…úňźt/",
          "Shoes / Éuňźz/",
          "Hat /h√¶t/",
          "Socks /s…íks/",
          "Gloves /…°l Ćvz/",
          "Bag /b√¶…°/",
          "Backpack /ňąb√¶k.p√¶k/",
          "Wallet /ňąw…íl.…™t/",
          "Color /ňąk Ćl.…ôr/",
          "Red /red/",
          "Yellow /ňąjel.…ô ä/",
          "Blue /bluňź/",
          "Green /…°riňźn/",
          "White /wa…™t/",
          "Black /bl√¶k/"
        ]
      },
      "17": {
        "name": "Primary colours",
        "vocabulary": [
          "Red /red/",
          "Yellow /ňąjel.…ô ä/",
          "Blue /bluňź/",
          "Green /…°riňźn/",
          "White /wa…™t/",
          "Black /bl√¶k/",
          "Color /ňąk Ćl.…ôr/"
        ]
      },
      "18": {
        "name": "Common adverbs of frequency",
        "notes": "always, often, often, not often, rarely, sometimes, never",
        "vocabulary": [
          "Often /ňą…íf.…ôn/",
          "Often /ňą…íf.…ôn/",
          "Usually /ňąjuňź. íu.…ô.li/",
          "Always /ňą…Ēňźl.we…™z/",
          "Sometimes /ňąs Ćm.ta…™mz/",
          "Never /ňąnev.…ôr/",
          "Every day /ňąev.ri de…™/",
          "Time /ta…™m/",
          "Time (frequency) /ta…™m/"
        ]
      },
      "19": {
        "name": "Appointments",
        "notes": "appointment, place, time, meet, tell, agree, problem, matter",
        "vocabulary": [
          "Time /ta…™m/",
          "Hour /a ä…ôr/",
          "Minute /ňąm…™n.…™t/",
          "Meet /miňźt/",
          "Together /t…ôňą…°e√į.…ôr/",
          "Go /…°…ô ä/",
          "Come /k Ćm/",
          "At /√¶t/",
          "Where /we…ôr/",
          "What time /w…ít ta…™m/",
          "Tomorrow /t…ôňąm…ír.…ô ä/",
          "Weekend /ňĆwiňźkňąend/",
          "OK /…ô äňąke…™/",
          "Question particle /ňąkwes.t É…ôn ňąp…Ďňź.t…™.k…ôl/",
          "OK /…ô äňąke…™/",
          "OK /…ô äňąke…™/",
          "No problem /n…ô ä ňąpr…íb.l…ôm/",
          "Sorry /ňąs…ír.i/",
          "Busy /ňąb…™z.i/",
          "Another day /…ôňąn Ć√į.…ôr de…™/"
        ]
      },
      "20": {
        "name": "Simple online communication",
        "notes": "hello, best regards, see you soon, thank you very much, goodbye",
        "vocabulary": [
          "Go online /…°…ô ä ňą…ín.la…™n/",
          "Net friend /net frend/",
          "Online /ňą…ín.la…™n/",
          "Computer /k…ômňąpjuňź.t…ôr/",
          "Mobile phone /ňąm…ô ä.ba…™l f…ô än/",
          "Phone /f…ô än/",
          "Make a call /me…™k …ô k…Ēňźl/",
          "Send /send/",
          "Message /ňąmes.…™d í/",
          "Email /ňąiňź.me…™l/",
          "WeChat /ňąwiňź.t É√¶t/",
          "Watch /w…ít É/",
          "Listen /ňąl…™s.…ôn/",
          "Video /ňąv…™d.i.…ô ä/"
        ]
      },
      "21": {
        "name": "Likes, dislikes, emotions, basic opinions",
        "vocabulary": [
          "Like /la…™k/",
          "Love /l Ćv/",
          "Dislike /d…™sňąla…™k/",
          "Hate /he…™t/",
          "Happy /ňąh√¶p.i/",
          "Sad /s√¶d/",
          "Angry /ňą√¶Ňč.…°ri/",
          "Tired /ta…™…ôd/",
          "Afraid /…ôňąfre…™d/",
          "Think /őł…™Ňčk/",
          "Consider /k…ônňąs…™d.…ôr/",
          "How? /ha ä/",
          "Good /…° äd/",
          "Correct /k…ôňąrekt/",
          "OK /…ô äňąke…™/",
          "Not OK /n…ít …ô äňąke…™/",
          "Maybe /ňąme…™.bi/",
          "Should / É äd/",
          "Really /ňąr…™…ô.li/",
          "Too /tuňź/",
          "Particle (change) /ňąp…Ďňź.t…™.k…ôl/",
          "Ah /…Ďňź/"
        ]
      },
      "22": {
        "name": "Travel and transportation",
        "vocabulary": [
          "Go /…°…ô ä/",
          "Come /k Ćm/",
          "Walk /w…Ēňźk/",
          "Ride /ra…™d/",
          "Vehicle /ňąviňź.…™.k…ôl/",
          "Train /tre…™n/",
          "Airplane /ňąe…ô.ple…™n/",
          "Subway /ňąs Ćb.we…™/",
          "Bus /b Ćs/",
          "Taxi /ňąt√¶k.si/",
          "Bicycle /ňąba…™.s…™.k…ôl/",
          "Walk /w…Ēňźk/",
          "Ticket /ňąt…™k.…™t/",
          "Buy ticket /ba…™ ňąt…™k.…™t/",
          "Station /ňąste…™. É…ôn/",
          "Airport /ňąe…ô.p…Ēňźt/",
          "Train station /tre…™n ňąste…™. É…ôn/",
          "Subway station /ňąs Ćb.we…™ ňąste…™. É…ôn/",
          "Road /r…ô äd/",
          "Intersection /ňĆ…™n.t…ôňąsek. É…ôn/",
          "Direction /da…™ňąrek. É…ôn/",
          "Left side /left sa…™d/",
          "Right side /ra…™t sa…™d/",
          "Front /fr Ćnt/",
          "Back /b√¶k/",
          "Far /f…Ďňźr/",
          "Near /n…™…ôr/",
          "Travel /ňątr√¶v.…ôl/",
          "Travel /ňątr√¶v.…ôl/",
          "Hotel /h…ô äňątel/",
          "Room /ruňźm/"
        ]
      },
      "23": {
        "name": "Seasons and weather",
        "notes": "summer, autumn, winter, weather, hot, cold, degree, sunny, cloudy, overcast, rain, snow",
        "vocabulary": [
          "Spring /spr…™Ňč/",
          "Summer /ňąs Ćm.…ôr/",
          "Autumn /ňą…Ēňź.t…ôm/",
          "Winter /ňąw…™n.t…ôr/",
          "Weather /ňąwe√į.…ôr/",
          "Hot /h…ít/",
          "Cold /k…ô äld/",
          "Warm /w…Ēňźm/",
          "Cool /kuňźl/",
          "Rain /re…™n/",
          "Snow /sn…ô ä/",
          "Windy /ňąw…™n.di/",
          "Sunny /ňąs Ćn.i/",
          "Cloudy /ňąkla ä.di/",
          "Cloudy /ňąkla ä.di/",
          "Temperature /ňątem.pr…ô.t É…ôr/"
        ]
      },
      "24": {
        "name": "Health",
        "notes": "comfortable, uncomfortable, sick, cold, body, get sick",
        "vocabulary": [
          "Body /ňąb…íd.i/",
          "Healthy /ňąhel.őłi/",
          "Get sick /…°et s…™k/",
          "Sick /s…™k/",
          "Hospital /ňąh…ís.p…™.t…ôl/",
          "Doctor /ňąd…ík.t…ôr/",
          "See a doctor /siňź …ô ňąd…ík.t…ôr/",
          "Take medicine /te…™k ňąmed.…™.s…ôn/",
          "Rest /rest/",
          "Exercise /ňąek.s…ô.sa…™z/",
          "Tired /ta…™…ôd/",
          "Pain /pe…™n/",
          "Catch a cold /k√¶t É …ô k…ô äld/"
        ]
      },
      "25": {
        "name": "Animals and nature",
        "notes": "animal, dog, cat, horse, mountain, sea, river",
        "vocabulary": [
          "Animal /ňą√¶n.…™.m…ôl/",
          "Cat /k√¶t/",
          "Dog /d…í…°/",
          "Bird /b…úňźd/",
          "Fish /f…™ É/",
          "Tree /triňź/",
          "Flower /ňąfla ä.…ôr/",
          "Grass /…°r…Ďňźs/",
          "Mountain /ňąma än.t…™n/",
          "Water /ňąw…Ēňź.t…ôr/",
          "River /ňąr…™v.…ôr/",
          "Sea /siňź/",
          "Park /p…Ďňźk/",
          "Nature /ňąne…™.t É…ôr/"
        ]
      }
    }
  }
}
